setup.py
gaussian_binom_dist/Binomialdistribution.py
gaussian_binom_dist/Gaussiandistribution.py
gaussian_binom_dist/Generaldistribution.py
gaussian_binom_dist/__init__.py
gaussian_binom_dist.egg-info/PKG-INFO
gaussian_binom_dist.egg-info/SOURCES.txt
gaussian_binom_dist.egg-info/dependency_links.txt
gaussian_binom_dist.egg-info/not-zip-safe
gaussian_binom_dist.egg-info/top_level.txt