Metadata-Version: 1.0
Name: gaussian-binom-dist
Version: 0.1
Summary: Gaussian distributions and binomial distributions
Home-page: UNKNOWN
Author: Cihan Evren
Author-email: cihan.evren2@outlook.com
License: UNKNOWN
Platform: UNKNOWN
